odoo/addons/hr_timesheet_analysis/README.rst
odoo/addons/hr_timesheet_analysis/__init__.py
odoo/addons/hr_timesheet_analysis/__manifest__.py
odoo/addons/hr_timesheet_analysis/i18n/de.po
odoo/addons/hr_timesheet_analysis/i18n/es.po
odoo/addons/hr_timesheet_analysis/i18n/hr_timesheet_analysis.pot
odoo/addons/hr_timesheet_analysis/readme/CONTRIBUTORS.rst
odoo/addons/hr_timesheet_analysis/readme/DESCRIPTION.rst
odoo/addons/hr_timesheet_analysis/readme/USAGE.rst
odoo/addons/hr_timesheet_analysis/static/description/icon.png
odoo/addons/hr_timesheet_analysis/static/description/index.html
odoo/addons/hr_timesheet_analysis/views/account_analytic_line.xml
odoo13_addon_hr_timesheet_analysis-13.0.1.0.1.dist-info/METADATA
odoo13_addon_hr_timesheet_analysis-13.0.1.0.1.dist-info/WHEEL
odoo13_addon_hr_timesheet_analysis-13.0.1.0.1.dist-info/top_level.txt
odoo13_addon_hr_timesheet_analysis-13.0.1.0.1.dist-info/RECORD
