Metadata-Version: 2.1
Name: odoo13-addon-hr-timesheet-analysis
Version: 13.0.1.0.1
Summary: Analyze tracked time in Pivot, Graph views
Home-page: https://github.com/OCA/timesheet
Author: Brainbean Apps, Odoo Community Association (OCA)
Author-email: support@odoo-community.org
License: AGPL-3
Platform: UNKNOWN
Classifier: Programming Language :: Python
Classifier: Framework :: Odoo
Classifier: License :: OSI Approved :: GNU Affero General Public License v3
Requires-Python: >=3.5
Requires-Dist: odoo (<13.1dev,>=13.0a)
